classifier_trains/__init__.py
classifier_trains/__main__.py
classifier_trains/core/__init__.py
classifier_trains/core/interface.py
classifier_trains/core/loading/__init__.py
classifier_trains/core/loading/dataloader.py
classifier_trains/core/model/__init__.py
classifier_trains/core/model/classifier.py
classifier_trains/core/model/facade.py
classifier_trains/core/model/utils.py
classifier_trains/core/preprocessing/__init__.py
classifier_trains/core/preprocessing/augmentation.py
classifier_trains/core/preprocessing/processor.py
classifier_trains/core/preprocessing/resize_and_padding.py
classifier_trains/schemas/__init__.py
classifier_trains/schemas/config.py
classifier_trains/schemas/constants.py
classifier_trains/schemas/pipeline.py
classifier_trains/utils/__init__.py
classifier_trains/utils/env.py
classifier_trains/utils/file.py
classifier_trains/utils/logger.py
classifier_trains/version.py
classifier_trains-1.2.4.dist-info/METADATA
classifier_trains-1.2.4.dist-info/WHEEL
classifier_trains-1.2.4.dist-info/RECORD
