Metadata-Version: 2.1
Name: classifier_trains
Version: 1.2.4
Summary: A PyTorch-based deep learning classifier training framework.
Home-page: https://pypi.org/project/classifier_trains/
License: MIT
Keywords: pytorch,deep learning,image classification
Author: wyhwong
Author-email: wyhwong@link.cuhk.edu.hk
Requires-Python: >=3.10,<4.0
Classifier: Intended Audience :: Developers
Classifier: License :: OSI Approved :: MIT License
Classifier: Natural Language :: English
Classifier: Operating System :: OS Independent
Classifier: Programming Language :: Python :: 3
Classifier: Programming Language :: Python :: 3.10
Classifier: Programming Language :: Python :: 3.11
Classifier: Programming Language :: Python :: 3.12
Classifier: Programming Language :: Python :: 3.13
Classifier: Topic :: Scientific/Engineering :: Artificial Intelligence
Classifier: Topic :: Software Development :: Libraries :: Python Modules
Requires-Dist: click (>=8.1.7,<9.0.0)
Requires-Dist: lightning (>=2.4.0,<3.0.0)
Requires-Dist: matplotlib (>=3.9.2,<4.0.0)
Requires-Dist: numpy (>=2.0.2,<3.0.0)
Requires-Dist: onnx (>=1.15.0,<2.0.0)
Requires-Dist: pydantic (>=2.8.2,<3.0.0)
Requires-Dist: pyyaml (>=6.0.1,<7.0.0)
Requires-Dist: scikit-learn (>=1.5.1,<2.0.0)
Requires-Dist: tensorboard (>=2.17.0,<3.0.0)
Requires-Dist: torch-tb-profiler (>=0.4.3,<0.5.0)
Project-URL: Repository, https://github.com/wyhwong/classifier-trains
